[
    {
        "caption": "Strings of twinkling lights softly danced in the background, setting the mood for an unforgettable intimate dinner in the garden. ✨\n\n@kibler_photography \n#earlymountainvineyards #virginiawedding #vineyardwedding #earlymountainwedding #virginia #charlottesvillewedding #vawedding #winerywedding #bride #dcwedding",
        "media_url": "https://scontent-sjc3-1.cdninstagram.com/v/t51.29350-15/242109721_147627914223961_5351462056493221932_n.jpg?_nc_cat=102&ccb=1-5&_nc_sid=8ae9d6&_nc_ohc=lA59_A_kXlEAX90Cx_c&_nc_ht=scontent-sjc3-1.cdninstagram.com&edm=ANQ71j8EAAAA&oh=a171bba83f802c9a5f5709e165a0866d&oe=6158393D",
        "media_type": "IMAGE",
        "id": "17874328004536814"
    },
    {
        "caption": "Just feeling it a little today 🌿💐 📸 @hannahjphotos",
        "media_url": "https://scontent-sjc3-1.cdninstagram.com/v/t51.29350-15/235561516_977034296471021_3767384296404416487_n.jpg?_nc_cat=105&ccb=1-5&_nc_sid=8ae9d6&_nc_ohc=eDxq_R1yyXUAX9P0BAR&_nc_ht=scontent-sjc3-1.cdninstagram.com&edm=ANQ71j8EAAAA&oh=f78d68bcd1ade07ee297ffd2161497f0&oe=6156C18D",
        "media_type": "IMAGE",
        "id": "17906406614062043"
    },
    {
        "caption": "We have been a little MIA over this way as we jumped head first into full blown wedding season 🙃 we are happy to finally be here, but boy are our feet sore! \n\nEndless thanks to our huge support system of staff and vendors alike 👏🏼 we couldn’t make the magic happen without you! 📸 @stephaniemessickphoto",
        "media_url": "https://scontent-sjc3-1.cdninstagram.com/v/t51.29350-15/205345872_1185214968611819_8944615942725436116_n.jpg?_nc_cat=107&ccb=1-5&_nc_sid=8ae9d6&_nc_ohc=LUk8lAW0TJkAX-oLKaM&_nc_ht=scontent-sjc3-1.cdninstagram.com&edm=ANQ71j8EAAAA&oh=43fdcd63b8a9ffd09d24056b994f4355&oe=61578704",
        "media_type": "IMAGE",
        "id": "18119734495231724"
    },
    {
        "caption": "The end of a night 🎆 and the beginning of a new chapter in life 🖤 📸 @wearethemitchells",
        "media_url": "https://scontent-sjc3-1.cdninstagram.com/v/t51.29350-15/179804533_1650438698479697_3026525716008336377_n.jpg?_nc_cat=101&ccb=1-5&_nc_sid=8ae9d6&_nc_ohc=-eFGUoAsg-AAX8nq7aR&_nc_ht=scontent-sjc3-1.cdninstagram.com&edm=ANQ71j8EAAAA&oh=4d928eb4147b97b731c62adcaadf9d79&oe=61586335",
        "media_type": "IMAGE",
        "id": "17925826048573677"
    },
    {
        "caption": "We have couples choose all kinds of different florals for our mantles, and chandeliers, but this romantic November display just took our breaths away 👏🏼 @blueridgefloraldesign knocked it out of the park again! 📸 @act_photo",
        "media_url": "https://scontent-sjc3-1.cdninstagram.com/v/t51.29350-15/177957766_269398471527978_8521279841614533450_n.jpg?_nc_cat=110&ccb=1-5&_nc_sid=8ae9d6&_nc_ohc=GCOr13waqosAX9pvLZP&_nc_ht=scontent-sjc3-1.cdninstagram.com&edm=ANQ71j8EAAAA&oh=b6a89d7fe1d9a7b8ab846022fab5d1b2&oe=61573FF7",
        "media_type": "IMAGE",
        "id": "17905243132768144"
    },
    {
        "caption": "Making me happy and hungry all in one picture 🎂 Always praising @cakesbyrachelbakeshop for her awesome job! 📸 @amynicolephoto",
        "media_url": "https://scontent-sjc3-1.cdninstagram.com/v/t51.29350-15/175847676_893937858069527_764849942583422669_n.jpg?_nc_cat=106&ccb=1-5&_nc_sid=8ae9d6&_nc_ohc=PoyQpQgPOv0AX9AYGvR&_nc_ht=scontent-sjc3-1.cdninstagram.com&edm=ANQ71j8EAAAA&oh=723c354c48c07384301249b3cd82e127&oe=6157D6C3",
        "media_type": "IMAGE",
        "id": "18153966430151021"
    },
    {
        "caption": "We are beyond ready to be getting this view again every weekend 🙌🏼 bring it on! 📸 @paigeryanphoto",
        "media_url": "https://scontent-sjc3-1.cdninstagram.com/v/t51.29350-15/174323321_192517069194242_2582312545649677441_n.jpg?_nc_cat=111&ccb=1-5&_nc_sid=8ae9d6&_nc_ohc=juAG8ELozccAX-bB_Ms&_nc_ht=scontent-sjc3-1.cdninstagram.com&edm=ANQ71j8EAAAA&oh=9fa1ca1cf5cb8bed34bb7a42f870cd34&oe=61575601",
        "media_type": "IMAGE",
        "id": "17889974693017835"
    },
    {
        "caption": "Oh Spring, we missed you 🌼 you better be here to stay! 📸 @finn.lively.photo",
        "media_url": "https://scontent-sjc3-1.cdninstagram.com/v/t51.29350-15/170726137_120098690170806_393569586869482937_n.jpg?_nc_cat=105&ccb=1-5&_nc_sid=8ae9d6&_nc_ohc=CThxXX5RiFEAX_WSb6W&_nc_oc=AQn7BKEoIf9GH7hzAq463SI98pmL1hcJcVqZF2n2zF7ewLupLXAniubk-FiX2QvXsAY&_nc_ht=scontent-sjc3-1.cdninstagram.com&edm=ANQ71j8EAAAA&oh=ad367a2ab99a84588cd95a5ce95ac135&oe=615819DD",
        "media_type": "IMAGE",
        "id": "17874454862273775"
    },
    {
        "caption": "As far as Swoon Saturdays go, you can't get much better than this 🖤 📸 @laurenmorrisphoto",
        "media_url": "https://scontent-sjc3-1.cdninstagram.com/v/t51.29350-15/169208063_946268112840904_8473170326493094415_n.jpg?_nc_cat=109&ccb=1-5&_nc_sid=8ae9d6&_nc_ohc=5Cy95sue3CsAX8xv_gJ&_nc_ht=scontent-sjc3-1.cdninstagram.com&edm=ANQ71j8EAAAA&oh=90bca2cf0f5aa8a8683c023a3b8e47cc&oe=6157083F",
        "media_type": "IMAGE",
        "id": "17911955812685409"
    },
    {
        "caption": "We are thrilled to announce that we have been working alongside the fantastic @anyvent_eventplanning to offer an All-Inclusive Micro Wedding Package to our prospective couples!  This is officially available starting today and we cannot wait to begin talking about it, and planning alongside this fantastic group of vendors! 🍾 📸 @rachelmayphoto",
        "media_url": "https://scontent-sjc3-1.cdninstagram.com/v/t51.29350-15/165248444_2739567589687143_3189975192478045324_n.jpg?_nc_cat=106&ccb=1-5&_nc_sid=8ae9d6&_nc_ohc=7vmBAZRPMI0AX_cEC97&_nc_ht=scontent-sjc3-1.cdninstagram.com&edm=ANQ71j8EAAAA&oh=176a9b7c8b7a53c5536aea82622b5080&oe=61581DD5",
        "media_type": "IMAGE",
        "id": "18192503794076559"
    },
    {
        "caption": "This gorgeous August day from last year was featured on @mtnsidebride yesterday and we couldn't be happier!  Elizabeth and Brian's day was intimate and safe during a tough time for the wedding world last year, it was an honor to host them! 📸 @aaronwatsonphotography",
        "media_url": "https://scontent-sjc3-1.cdninstagram.com/v/t51.29350-15/162114204_451695589615823_2435793767340872911_n.jpg?_nc_cat=103&ccb=1-5&_nc_sid=8ae9d6&_nc_ohc=Pj0ZwIqUdxQAX_FCv80&_nc_ht=scontent-sjc3-1.cdninstagram.com&edm=ANQ71j8EAAAA&oh=6c14dcab4656140eb3cbf51e66955b35&oe=6156D6BA",
        "media_type": "IMAGE",
        "id": "17876376752264768"
    },
    {
        "caption": "Wouldn't be St. Patrick's Day without a little green and orange 💚 🍀 hope everyone enjoyed a bit of luck today!",
        "media_url": "https://scontent-sjc3-1.cdninstagram.com/v/t51.29350-15/161640522_184500693251057_686315913822866560_n.jpg?_nc_cat=107&ccb=1-5&_nc_sid=8ae9d6&_nc_ohc=f0BORteJGb4AX-mSRe-&_nc_ht=scontent-sjc3-1.cdninstagram.com&edm=ANQ71j8EAAAA&oh=34e35576483f59bdc28a98f074b4955f&oe=6156B9BB",
        "media_type": "IMAGE",
        "id": "17893545424941948"
    },
    {
        "caption": "Candlelight and a preset salad make for a pretty great start to any reception evening 😋 📸 @kayteelauren",
        "media_url": "https://scontent-sjc3-1.cdninstagram.com/v/t51.29350-15/158605178_2621421234817708_566070206015382122_n.jpg?_nc_cat=110&ccb=1-5&_nc_sid=8ae9d6&_nc_ohc=E1L2fJA0WTkAX-VzsDJ&_nc_ht=scontent-sjc3-1.cdninstagram.com&edm=ANQ71j8EAAAA&oh=2a10173ec3214ce5cae59241c732f3a2&oe=6157683C",
        "media_type": "IMAGE",
        "id": "18123076324170502"
    },
    {
        "caption": "We don't need a ton of words for a picture like this ☀️ 💙 😊 📸 @finn.lively.photo",
        "media_url": "https://scontent-sjc3-1.cdninstagram.com/v/t51.29350-15/156592919_2934686333519032_5218177218226992859_n.jpg?_nc_cat=104&ccb=1-5&_nc_sid=8ae9d6&_nc_ohc=aQxiY68msVwAX_xTsr2&_nc_ht=scontent-sjc3-1.cdninstagram.com&edm=ANQ71j8EAAAA&oh=5d63778e419de4e99da2e60091a0329e&oe=61579590",
        "media_type": "IMAGE",
        "id": "17918558911573635"
    },
    {
        "caption": "Draping is such a beautiful option to add your own unique touch to our space 🤍 look how gorgeous and dreamy this space looks! 📸 @vickigrafton",
        "media_url": "https://scontent-sjc3-1.cdninstagram.com/v/t51.29350-15/155864819_741003903223635_6909116607353228611_n.jpg?_nc_cat=106&ccb=1-5&_nc_sid=8ae9d6&_nc_ohc=Jn4h_ugxhpcAX8e8nQS&_nc_ht=scontent-sjc3-1.cdninstagram.com&edm=ANQ71j8EAAAA&oh=25c9b7d15b81800c105ade5321e0cee1&oe=6157D8F6",
        "media_type": "IMAGE",
        "id": "17880912800129203"
    },
    {
        "caption": "Giving off all the Winter wedding vibes 👏🏼 the cozy ambiance that the Event Hall provides is perfect for this time of year 📸 @kristencamiellephoto",
        "media_url": "https://scontent-sjc3-1.cdninstagram.com/v/t51.29350-15/150284260_1319305348436665_8704171548429090663_n.jpg?_nc_cat=107&ccb=1-5&_nc_sid=8ae9d6&_nc_ohc=zkdvfi86gQ0AX-cf-kc&_nc_ht=scontent-sjc3-1.cdninstagram.com&edm=ANQ71j8EAAAA&oh=9f6dfaf6ee9c8c0345c6ea56302c2bb3&oe=6156CAFD",
        "media_type": "IMAGE",
        "id": "17896895200817608"
    },
    {
        "caption": "There is something so romantic about film photography 🎞 adds such a classical quality to the memories of your big day! 📸 @peytoncurry",
        "media_url": "https://scontent-sjc3-1.cdninstagram.com/v/t51.29350-15/153085896_452827452537447_3035367678377150132_n.jpg?_nc_cat=104&ccb=1-5&_nc_sid=8ae9d6&_nc_ohc=T2XTmOwsTIoAX9EVBvA&_nc_ht=scontent-sjc3-1.cdninstagram.com&edm=ANQ71j8EAAAA&oh=caa5c23b29541c8a643cb09eeade49e9&oe=6157B3DD",
        "media_type": "IMAGE",
        "id": "17901312130770458"
    },
    {
        "caption": "Loving our tablescape for this intimate celebration this past September for Chelsea and John 🍾 Thank you for letting us be a part of your special day! 📸 @kibler_photography",
        "media_url": "https://scontent-sjc3-1.cdninstagram.com/v/t51.29350-15/152793226_433685894403820_8270169107536585997_n.jpg?_nc_cat=103&ccb=1-5&_nc_sid=8ae9d6&_nc_ohc=34DazyfD0QYAX8YzMqI&_nc_ht=scontent-sjc3-1.cdninstagram.com&edm=ANQ71j8EAAAA&oh=2924e94fcb6f6645e042d4e3d54cec1a&oe=61588491",
        "media_type": "IMAGE",
        "id": "17899046899754181"
    },
    {
        "caption": "We are missing our Wine Library all decked out for a small event right now 🖤 hoping to get back to it later this year with some beautiful Rehearsal Dinners! 📸 @amynicolephoto",
        "media_url": "https://scontent-sjc3-1.cdninstagram.com/v/t51.29350-15/151474672_174987557474263_2479069146143644699_n.jpg?_nc_cat=105&ccb=1-5&_nc_sid=8ae9d6&_nc_ohc=h8GHoyEc0HAAX8S7mv2&_nc_ht=scontent-sjc3-1.cdninstagram.com&edm=ANQ71j8EAAAA&oh=766be6e36d8f9c8866d24715099486f9&oe=61584BC1",
        "media_type": "IMAGE",
        "id": "17904713962704180"
    },
    {
        "caption": "Having someone to laugh with until the end is the real gift ❤️ cheers to all our Valentines 📸 @peytoncurry",
        "media_url": "https://scontent-sjc3-1.cdninstagram.com/v/t51.29350-15/150195741_113610457390508_3368219484734432480_n.jpg?_nc_cat=109&ccb=1-5&_nc_sid=8ae9d6&_nc_ohc=sY0Gwdb-zGsAX-W_UmY&_nc_ht=scontent-sjc3-1.cdninstagram.com&edm=ANQ71j8EAAAA&oh=07c81e7e44e9d1a6eec7c6e2db16f198&oe=6157D208",
        "media_type": "IMAGE",
        "id": "17938538428440884"
    }
]